consistize/__init__.py
consistize/core.py
consistize-0.1.0.dist-info/METADATA
consistize-0.1.0.dist-info/WHEEL
consistize-0.1.0.dist-info/top_level.txt
consistize-0.1.0.dist-info/RECORD
