Metadata-Version: 2.4
Name: consistize
Version: 0.1.0
Summary: Image consistency checks with OpenAI vision models.
Requires-Python: >=3.9
Requires-Dist: openai>=1.40.0
